{"nodes": [{"id": "type_resolution_roadmap_doc", "label": "type-resolution-roadmap.md", "file_type": "document", "source_file": "type-resolution-roadmap.md"}, {"id": "type_resolution_roadmap_principles", "label": "Type Resolution Principles", "file_type": "document", "source_file": "type-resolution-roadmap.md"}, {"id": "type_resolution_roadmap_phase9", "label": "Phase 9: Return-Type-Aware Variable Binding", "file_type": "document", "source_file": "type-resolution-roadmap.md"}], "edges": [], "hyperedges": []}